MANIFEST.in
README.md
setup.py
talklink/__init__.py
talklink/assign_speakers.py
talklink/download.py
talklink/extract_claims.py
talklink/generate_about_page.py
talklink/generate_all_videos_page.py
talklink/generate_speaker_map.py
talklink/generate_talklink_page.py
talklink/generate_toc_page.py
talklink/models.py
talklink/transcribe.py
talklink.egg-info/PKG-INFO
talklink.egg-info/SOURCES.txt
talklink.egg-info/dependency_links.txt
talklink.egg-info/requires.txt
talklink.egg-info/top_level.txt
talklink/resources/.DS_Store
talklink/resources/about/script.js
talklink/resources/about/styles.css
talklink/resources/about/template.md
talklink/resources/all_videos/script.js
talklink/resources/all_videos/styles.css
talklink/resources/all_videos/template.md
talklink/resources/table_of_contents/script.js
talklink/resources/table_of_contents/styles.css
talklink/resources/table_of_contents/template.md
talklink/resources/talklink_page/.DS_Store
talklink/resources/talklink_page/index.html
talklink/resources/talklink_page/info-icon-svgrepo-com.svg
talklink/resources/talklink_page/script.js
talklink/resources/talklink_page/styles.css
talklink/resources/talklink_page/template.md