Metadata-Version: 2.2
Name: talklink
Version: 0.0.31
Summary: Create a talklink page from a youtube video
Author: David Schneck
Author-email: president@remoria.ai
Requires-Python: >=3.10
Requires-Dist: yt-dlp
Requires-Dist: openai
Requires-Dist: tiktoken
Requires-Dist: pydantic
Requires-Dist: jinja2
Requires-Dist: assemblyai
Requires-Dist: requests
Requires-Dist: librosa
Requires-Dist: soundfile
Dynamic: author
Dynamic: author-email
Dynamic: requires-dist
Dynamic: requires-python
Dynamic: summary
